Metadata-Version: 2.1
Name: pacoteira_do_verao
Version: 0.1.0
Summary: An example package. Generated with cookiecutter-pylibrary.
Home-page: https://LucianoBatista.github.io/pacoteira_do_verao/
Author: "Luba"
Author-email: "Luba" <luciano.eq@outlook.com>
License: MIT license
Classifier: License :: OSI Approved :: MIT License
Requires-Python: >=3.10
License-File: LICENSE
